data/diaeresis.json
data/diaeresis_cyrano.json
data/diaeresis_empty.json
data/occurrences
plint/__init__.py
plint/__main__.py
plint/chunk.py
plint/chunks.py
plint/common.py
plint/diaeresis.py
plint/error.py
plint/hyphen_splitter.py
plint/localization.py
plint/nature.py
plint/options.py
plint/pattern.py
plint/rhyme.py
plint/template.py
plint/verse.py
plint/vowels.py
plint/tests/__init__.py
plint/tests/test_aspirated_counts.py
plint/tests/test_bad_chars.py
plint/tests/test_bad_counts.py
plint/tests/test_counts.py
plint/tests/test_disjunct.py
plint/tests/test_eliminate.py
plint/tests/test_exceptions_count.py
plint/tests/test_gender.py
plint/tests/test_hiatus.py
plint/tests/test_poem_counts.py
plint/tests/test_real_counts.py
plint/tests/test_rhyme.py
plint/tests/test_rm_accents.py
plint/tests/test_sanity_check.py
plint/tests/test_sanity_check2.py
plint/tests/test_sigle_count.py
plint/tests/test_simple_counts.py
plint/tests/test_template.py
plint-0.1.dist-info/COPYING
plint-0.1.dist-info/LICENSE_bottle
plint-0.1.dist-info/METADATA
plint-0.1.dist-info/WHEEL
plint-0.1.dist-info/entry_points.txt
plint-0.1.dist-info/top_level.txt
plint-0.1.dist-info/RECORD
