Metadata-Version: 2.1
Name: plint
Version: 0.1
Summary: French poetry validator
Home-page: https://gitlab.com/a3nm/plint
Author: Antoine Amarilli
Author-email: a3nm@a3nm.net
License: UNKNOWN
Platform: UNKNOWN
Classifier: Programming Language :: Python :: 3
